jax/apiutils/__init__.py
jax/apiutils/exceptions.py
jax/apiutils/fastapi/__init__.py
jax/apiutils/fastapi/const/__init__.py
jax/apiutils/fastapi/const/messages.py
jax/apiutils/fastapi/enum.py
jax/apiutils/fastapi/exceptions/__init__.py
jax/apiutils/fastapi/exceptions/auth.py
jax/apiutils/fastapi/responses.py
jax/apiutils/fastapi/schemas/__init__.py
jax/apiutils/fastapi/schemas/user.py
jax/apiutils/fastapi/types.py
jax/apiutils/responses.py
jax/apiutils/schemas/__init__.py
jax/apiutils/schemas/dataclasses.py
jax/apiutils/schemas/pydantic/__init__.py
jax/apiutils/schemas/pydantic/core.py
jax/apiutils/schemas/pydantic/exceptions.py
jax/apiutils/schemas/pydantic/paging.py
jax/apiutils/schemas/pydantic/server_sent_event.py
jax/apiutils/types.py
jax_apiutils-0.2.0a3.dist-info/LICENSE
jax_apiutils-0.2.0a3.dist-info/METADATA
jax_apiutils-0.2.0a3.dist-info/WHEEL
jax_apiutils-0.2.0a3.dist-info/RECORD
